spectral_trust/__init__.py
spectral_trust/__main__.py
spectral_trust/config.py
spectral_trust/framework.py
spectral_trust/graph.py
spectral_trust/instrumentation.py
spectral_trust/spectral.py
spectral_trust/cli/__init__.py
spectral_trust/cli/__main__.py
spectral_trust/cli/diagnosis.py
spectral_trust-0.1.4.dist-info/LICENSE
spectral_trust-0.1.4.dist-info/METADATA
spectral_trust-0.1.4.dist-info/WHEEL
spectral_trust-0.1.4.dist-info/entry_points.txt
spectral_trust-0.1.4.dist-info/top_level.txt
spectral_trust-0.1.4.dist-info/RECORD
