Metadata-Version: 2.1
Name: spectral_trust
Version: 0.1.4
Summary: Spectral diagnostics for trust in LLMs
Author: Valentin Noël
Author-email: val.noel@proton.me
Requires-Python: >=3.8
License-File: LICENSE
Requires-Dist: numpy
Requires-Dist: pandas
Requires-Dist: matplotlib
Requires-Dist: seaborn
Requires-Dist: scipy
Requires-Dist: torch>=2.0.0
Requires-Dist: transformers>=4.30.0
Requires-Dist: tqdm
Requires-Dist: accelerate
